pyrfd/__init__.py
pyrfd/batchsize.py
pyrfd/covariance.py
pyrfd/optimizer.py
pyrfd/plots.py
pyrfd/regression.py
pyrfd/sampling.py
pyrfd-1.0.1.dist-info/METADATA
pyrfd-1.0.1.dist-info/WHEEL
pyrfd-1.0.1.dist-info/RECORD
