Metadata-Version: 2.1
Name: pyrfd
Version: 1.0.1
Summary: 
Author: Felix Benning
Author-email: felix.benning@gmail.com
Requires-Python: >=3.9,<4.0
Classifier: Programming Language :: Python :: 3
Classifier: Programming Language :: Python :: 3.9
Classifier: Programming Language :: Python :: 3.10
Classifier: Programming Language :: Python :: 3.11
Classifier: Programming Language :: Python :: 3.12
Classifier: Programming Language :: Python :: 3.13
Requires-Dist: lightning (>=2.2.4,<3.0.0)
Requires-Dist: matplotlib (>=3.8.3,<4.0.0)
Requires-Dist: numpy (>=1.26.4,<2.0.0)
Requires-Dist: pandas (>=2.2.0,<3.0.0)
Requires-Dist: scikit-learn (>=1.4.1.post1,<2.0.0)
Requires-Dist: tensorboard (>=2.16.2,<3.0.0)
Requires-Dist: torch (>=2.2.0,<3.0.0)
Requires-Dist: torchmetrics (>=1.4.0,<2.0.0)
Requires-Dist: torchsummary (>=1.5.1,<2.0.0)
Requires-Dist: torchvision (>=0.17.0,<0.18.0)
Requires-Dist: tqdm (>=4.66.2,<5.0.0)
